am2eda/__init__.py
am2eda/backup_code.py
am2eda/eda_simple.py
am2eda/plot.py
am2eda/process.py
am2eda/txt2pkl.py
am2eda-0.0.0.2.dist-info/METADATA
am2eda-0.0.0.2.dist-info/WHEEL
am2eda-0.0.0.2.dist-info/top_level.txt
am2eda-0.0.0.2.dist-info/RECORD
