Metadata-Version: 2.1
Name: am2eda
Version: 0.0.0.2
Summary: UNKNOWN
Home-page: UNKNOWN
License: UNKNOWN
Platform: UNKNOWN
Requires-Python: >=3.6
Requires-Dist: numpy
Requires-Dist: pandas
Requires-Dist: scipy
Requires-Dist: scikit-learn
Requires-Dist: seaborn
Requires-Dist: statsmodels
Requires-Dist: tqdm
Requires-Dist: umap-learn
Requires-Dist: plotly
Requires-Dist: nbformat >=4.2.0
Requires-Dist: Cython <3
Requires-Dist: ipykernel
Requires-Dist: hdbscan
Requires-Dist: bokeh
Requires-Dist: autogluon
